Workbook

Sheet Summary
A1: STRADA INTELLIGENCE — BUG TRACKER SUMMARY
A3: Total Bugs Logged | B3: =COUNTA(BugLog[Bug ID]) -> 1
A4: Open (not closed/rejected) | B4: =B3-COUNTIF(BugLog[Status],"Verified / Closed")-COUNTIF(BugLog[Status],"Won't Fix")-COUNTIF(BugLog[Status],"Duplicate")-COUNTIF(BugLog[Status],"Cannot Reproduce") -> 1
A5: Closed / Verified | B5: =COUNTIF(BugLog[Status],"Verified / Closed") -> 0
A6: Avg Days Open | B6: =IFERROR(ROUND(AVERAGE(BugLog[Days Open]),0),0) -> 0
A8: By Status | B8: Count | D8: By Priority | E8: Count
A9: =Lists!A2 -> New | B9: =COUNTIF(BugLog[Status],A9) -> 0 | D9: =Lists!B2 -> P0 - Critical | E9: =COUNTIF(BugLog[Priority],D9) -> 0
A10: =Lists!A3 -> Triaged | B10: =COUNTIF(BugLog[Status],A10) -> 1 | D10: =Lists!B3 -> P1 - High | E10: =COUNTIF(BugLog[Priority],D10) -> 0
A11: =Lists!A4 -> In Progress | B11: =COUNTIF(BugLog[Status],A11) -> 0 | D11: =Lists!B4 -> P2 - Medium | E11: =COUNTIF(BugLog[Priority],D11) -> 1
A12: =Lists!A5 -> Blocked | B12: =COUNTIF(BugLog[Status],A12) -> 0 | D12: =Lists!B5 -> P3 - Low | E12: =COUNTIF(BugLog[Priority],D12) -> 0
A13: =Lists!A6 -> In Review | B13: =COUNTIF(BugLog[Status],A13) -> 0
A14: =Lists!A7 -> Fixed - Pending Verification | B14: =COUNTIF(BugLog[Status],A14) -> 0 | D14: By Dashboard Section | E14: Count
A15: =Lists!A8 -> Verified / Closed | B15: =COUNTIF(BugLog[Status],A15) -> 0 | D15: =Lists!D2 -> 1. Verdict / Headline Score | E15: =COUNTIF(BugLog[Dashboard Section],D15) -> 0
A16: =Lists!A9 -> Reopened | B16: =COUNTIF(BugLog[Status],A16) -> 0 | D16: =Lists!D3 -> 2. KPI Tiles | E16: =COUNTIF(BugLog[Dashboard Section],D16) -> 0
A17: =Lists!A10 -> Won't Fix | B17: =COUNTIF(BugLog[Status],A17) -> 0 | D17: =Lists!D4 -> 3. Seven Pillars | E17: =COUNTIF(BugLog[Dashboard Section],D17) -> 0
A18: =Lists!A11 -> Duplicate | B18: =COUNTIF(BugLog[Status],A18) -> 0 | D18: =Lists!D5 -> 4. Property Mix | E18: =COUNTIF(BugLog[Dashboard Section],D18) -> 0
A19: =Lists!A12 -> Cannot Reproduce | B19: =COUNTIF(BugLog[Status],A19) -> 0 | D19: =Lists!D6 -> 5. 9-Month Trend Charts | E19: =COUNTIF(BugLog[Dashboard Section],D19) -> 0
D20: =Lists!D7 -> 6. Asking Price Per Sq Ft | E20: =COUNTIF(BugLog[Dashboard Section],D20) -> 0
D21: =Lists!D8 -> 7. Transaction Volume by Area | E21: =COUNTIF(BugLog[Dashboard Section],D21) -> 0
D22: =Lists!D9 -> 8. Rental Yield by Property Type | E22: =COUNTIF(BugLog[Dashboard Section],D22) -> 0
D23: =Lists!D10 -> 9. Recent Sales Transactions | E23: =COUNTIF(BugLog[Dashboard Section],D23) -> 0
D24: =Lists!D12 -> Global / Site-wide (header, nav, layout) | E24: =COUNTIF(BugLog[Dashboard Section],D24) -> 0
D25: =Lists!D13 -> Data Pipeline / Backend | E25: =COUNTIF(BugLog[Dashboard Section],D25) -> 0

Sheet Bug Log
A1: STRADA INTELLIGENCE — WEBSITE BUG TRACKER
A2: Log every bug — large or small. Use the dropdowns to keep categories consistent for the review team. New rows auto-extend the table.
A3: Bug ID | B3: Date Reported | C3: Reported By | D3: Status | E3: Priority | F3: Severity | G3: Title / Summary | H3: Dashboard Section | I3: Bug Category / Type | J3: Affected Data Source | K3: Environment | L3: Browser / Device | M3: Steps to Reproduce | N3: Expected Result | O3: Actual Result | P3: Frequency | Q3: Screenshot / Link | R3: Assigned To | S3: Date Resolved | T3: Days Open | U3: Root Cause | V3: Resolution / Notes
A4: BUG-001 | B4: 22/06/2026 | C4: Kyle | D4: Triaged | E4: P2 - Medium | F4: S3 - Major | G4: Total listing volume for rent is showing an abnormally large number for Jumeirah Village Circle (28020 listings) which could suggest file dump is not de duping. I manually checked on propertyfinder and this many listings did not come up. | H4: 10.Lising volume | I4: Data Accuracy (wrong value) | J4: Property Portal Data | K4: Development | L4: Chrome 126 / Desktop | M4: 1. Open dashboard. 2. View Listing data | N4: Figure should be around 15,000 or 18,000 | O4: Tile reads around 28,000 | P4: Always (100%) | R4: Data Team | T4: =IF(BugLog[[#This Row],[Date Reported]]="","",IF(BugLog[[#This Row],[Date Resolved]]="",TODAY()-BugLog[[#This Row],[Date Reported]],BugLog[[#This Row],[Date Resolved]]-BugLog[[#This Row],[Date Reported]])) -> #VALUE! | V4: Suspect currency aggregation dropping AED-denominated rows.
T5: =IF(BugLog[[#This Row],[Date Reported]]="","",IF(BugLog[[#This Row],[Date Resolved]]="",TODAY()-BugLog[[#This Row],[Date Reported]],BugLog[[#This Row],[Date Resolved]]-BugLog[[#This Row],[Date Reported]]))
T6: =IF(BugLog[[#This Row],[Date Reported]]="","",IF(BugLog[[#This Row],[Date Resolved]]="",TODAY()-BugLog[[#This Row],[Date Reported]],BugLog[[#This Row],[Date Resolved]]-BugLog[[#This Row],[Date Reported]]))

Sheet Lists
A1: Status | B1: Priority | C1: Severity | D1: Dashboard Section | E1: Bug Category / Type | F1: Affected Data Source | G1: Environment | H1: Frequency
A2: New | B2: P0 - Critical | C2: S1 - Blocker | D2: 1. Verdict / Headline Score | E2: Data Accuracy (wrong value) | F2: DLD Transactions | G2: Production | H2: Always (100%)
A3: Triaged | B3: P1 - High | C3: S2 - Critical | D3: 2. KPI Tiles | E3: Data Freshness / Stale Data | F3: Rental Yield Data | G3: Staging | H3: Often
A4: In Progress | B4: P2 - Medium | C4: S3 - Major | D4: 3. Seven Pillars | E4: Missing / No Data | F4: Asking Prices | G4: Development | H4: Sometimes
A5: Blocked | B5: P3 - Low | C5: S4 - Minor | D5: 4. Property Mix | E5: Calculation / Logic Error | F5: Oil / Brent Price | H5: Rarely
A6: In Review | C6: S5 - Cosmetic | D6: 5. 9-Month Trend Charts | E6: Chart / Visualization | F6: Interest Rates | H6: Once
A7: Fixed - Pending Verification | D7: 6. Asking Price Per Sq Ft | E7: UI / Layout / Styling | F7: Stock Markets (UAE / Gulf)
A8: Verified / Closed | D8: 7. Transaction Volume by Area | E8: Functional / Broken Feature | F8: News / Geopolitics Feed
A9: Reopened | D9: 8. Rental Yield by Property Type | E9: Navigation / Broken Link | F9: Tourism / Aviation Data
A10: Won't Fix | D10: 9. Recent Sales Transactions | E10: Performance / Slow Load | F10: Developer Financials
A11: Duplicate | D11: 10.Lising volume | E11: Responsive / Mobile | F11: Multiple / Mixed
A12: Cannot Reproduce | D12: Global / Site-wide (header, nav, layout) | E12: Accessibility | F12: N/A (UI only)
D13: Data Pipeline / Backend | E13: Content / Copy / Label | F13: Property Portal Data
E14: Data Source / API Integration
E15: Security
E16: Other
